{"_path":"/linux/ubuntu_002","_dir":"linux","_draft":false,"_partial":false,"_locale":"","_empty":false,"title":"ubuntu 18.04 dock에 프로그램 등록하기","description":"우분투 18.04 dock에 프로그램 등록하기","cover":"/img/linux/ubuntu-003-01.png","date":"2020-02-22T00:00:00.000Z","layout":"article","body":{"type":"root","children":[{"type":"element","tag":"h1","props":{"id":"ubuntu-1804-dock에-프로그램-등록하기"},"children":[{"type":"text","value":"ubuntu 18.04 dock에 프로그램 등록하기"}]},{"type":"element","tag":"p","props":{},"children":[{"type":"text","value":"새로 설치한 우분투의 데스크탑 독에 프로그램을 등록하고자 한다.\r\n등록할 것은 스프링 툴 sts-4.5.1 이다."}]},{"type":"element","tag":"p","props":{},"children":[{"type":"text","value":"스프링 툴 압축 푼 것은 아래처럼 폴더에 위치해 있다.\r\nSpringToolSuite4가 실행파일이고  icon.xpm이 아이콘 파일이다."}]},{"type":"element","tag":"code","props":{"code":"kyin@kyin:~/dev/sts-4.5.1.RELEASE$ pwd \r\n/home/kyin/dev/sts-4.5.1.RELEASE \r\n\r\nkyin@kyin:~/dev/sts-4.5.1.RELEASE$ ls \r\nMETA-INF \r\n...\r\nSpringToolSuite4 \r\nicon.xpm\r\n...\n","language":"bsh","meta":null},"children":[{"type":"element","tag":"pre","props":{},"children":[{"type":"element","tag":"code","props":{"__ignoreMap":""},"children":[{"type":"element","tag":"div","props":{"class":"line"},"children":[{"type":"element","tag":"span","props":{},"children":[{"type":"text","value":"kyin@kyin:~/dev/sts-4.5.1.RELEASE$ pwd \r\n/home/kyin/dev/sts-4.5.1.RELEASE \r\n\r\nkyin@kyin:~/dev/sts-4.5.1.RELEASE$ ls \r\nMETA-INF \r\n...\r\nSpringToolSuite4 \r\nicon.xpm\r\n..."}]}]}]}]}]},{"type":"element","tag":"p","props":{},"children":[{"type":"text","value":"프로그램 실행 아이콘을 만들기 위해 자신의 홈디렉토리 아래 "},{"type":"element","tag":"code-inline","props":{},"children":[{"type":"text","value":"~/.local/share/applications"}]},{"type":"text","value":" 폴더에 "},{"type":"element","tag":"code-inline","props":{},"children":[{"type":"text","value":".desktop"}]},{"type":"text","value":" 파일을 만든다."}]},{"type":"element","tag":"p","props":{},"children":[{"type":"text","value":"나의 경우는 "},{"type":"element","tag":"code-inline","props":{},"children":[{"type":"text","value":"sts.desktop"}]},{"type":"text","value":"으로 만들었다."}]},{"type":"element","tag":"code","props":{"code":"$ cd ~/.local/share/applications/\r\n$ vi sts.desktop\r\n\r\n[Desktop Entry]\r\nName=sts-4.5.1.RELEASE\r\nExec=/home/kyin/dev/sts-4.5.1.RELEASE/SpringToolSuite4\r\nComment=Sprint Tool Suite 4.5.1\r\nTerminal=false\r\nType=Application\r\nIcon=/home/kyin/dev/sts-4.5.1.RELEASE/icon.xpm\n","language":"bsh","meta":null},"children":[{"type":"element","tag":"pre","props":{},"children":[{"type":"element","tag":"code","props":{"__ignoreMap":""},"children":[{"type":"element","tag":"div","props":{"class":"line"},"children":[{"type":"element","tag":"span","props":{},"children":[{"type":"text","value":"$ cd ~/.local/share/applications/\r\n$ vi sts.desktop\r\n\r\n[Desktop Entry]\r\nName=sts-4.5.1.RELEASE\r\nExec=/home/kyin/dev/sts-4.5.1.RELEASE/SpringToolSuite4\r\nComment=Sprint Tool Suite 4.5.1\r\nTerminal=false\r\nType=Application\r\nIcon=/home/kyin/dev/sts-4.5.1.RELEASE/icon.xpm"}]}]}]}]}]},{"type":"element","tag":"p","props":{},"children":[{"type":"element","tag":"code-inline","props":{},"children":[{"type":"text","value":"sts.desktop"}]},{"type":"text","value":" 파일을 생성 후에 프로그램 목록을 열어보면 추가한 스프링툴 아이콘이 표시될 것이고 우클릭하여 "},{"type":"element","tag":"code-inline","props":{},"children":[{"type":"text","value":"즐겨찾기에 추가"}]},{"type":"text","value":"를 선택해주면 독에 아이콘이 생성된다."}]},{"type":"element","tag":"p","props":{},"children":[{"type":"element","tag":"img","props":{"alt":"즐겨찾기에 추가 하기","src":"/img/linux/ubuntu-003-01.png"},"children":[]}]}],"toc":{"title":"","searchDepth":2,"depth":2,"links":[]}},"_type":"markdown","_id":"content:linux:003.ubuntu_002.md","_source":"content","_file":"linux/003.ubuntu_002.md","_extension":"md"}